azure/mgmt/edgeorder/__init__.py
azure/mgmt/edgeorder/_configuration.py
azure/mgmt/edgeorder/_edge_order_management_client.py
azure/mgmt/edgeorder/_patch.py
azure/mgmt/edgeorder/_serialization.py
azure/mgmt/edgeorder/_vendor.py
azure/mgmt/edgeorder/_version.py
azure/mgmt/edgeorder/py.typed
azure/mgmt/edgeorder/aio/__init__.py
azure/mgmt/edgeorder/aio/_configuration.py
azure/mgmt/edgeorder/aio/_edge_order_management_client.py
azure/mgmt/edgeorder/aio/_patch.py
azure/mgmt/edgeorder/aio/_vendor.py
azure/mgmt/edgeorder/aio/operations/__init__.py
azure/mgmt/edgeorder/aio/operations/_edge_order_management_client_operations.py
azure/mgmt/edgeorder/aio/operations/_patch.py
azure/mgmt/edgeorder/models/__init__.py
azure/mgmt/edgeorder/models/_edge_order_management_client_enums.py
azure/mgmt/edgeorder/models/_models_py3.py
azure/mgmt/edgeorder/models/_patch.py
azure/mgmt/edgeorder/operations/__init__.py
azure/mgmt/edgeorder/operations/_edge_order_management_client_operations.py
azure/mgmt/edgeorder/operations/_patch.py
azure_mgmt_edgeorder-2.0.0.dist-info/LICENSE
azure_mgmt_edgeorder-2.0.0.dist-info/METADATA
azure_mgmt_edgeorder-2.0.0.dist-info/WHEEL
azure_mgmt_edgeorder-2.0.0.dist-info/top_level.txt
azure_mgmt_edgeorder-2.0.0.dist-info/RECORD
